p8hub/__init__.py
p8hub/app.py
p8hub/app_info.py
p8hub/config.py
p8hub/database.py
p8hub/globals.py
p8hub/utils.py
p8hub/apps/.DS_Store
p8hub/apps/doctr/Dockerfile
p8hub/apps/doctr/build.sh
p8hub/apps/doctr/docker-compose.yml
p8hub/apps/doctr/p8hub.app.yml
p8hub/apps/doctr/src/app.py
p8hub/apps/doctr/src/requirements.txt
p8hub/apps/doctr/src/backend/tensorflow.py
p8hub/apps/ollama/docker-compose.yml
p8hub/apps/ollama/p8hub.app.yml
p8hub/apps/teachable-ai/docker-compose.yml
p8hub/apps/teachable-ai/p8hub.app.yml
p8hub/apps/tts-generation-webui/docker-compose.yml
p8hub/apps/tts-generation-webui/p8hub.app.yml
p8hub/apps/whishper/.env
p8hub/apps/whishper/docker-compose.yml
p8hub/apps/whishper/nginx.conf
p8hub/apps/whishper/p8hub.app.yml
p8hub/core/__init__.py
p8hub/core/app_manager.py
p8hub/core/exceptions.py
p8hub/core/service_manager.py
p8hub/frontend-dist/.DS_Store
p8hub/frontend-dist/404.html
p8hub/frontend-dist/favicon.ico
p8hub/frontend-dist/index.html
p8hub/frontend-dist/index.txt
p8hub/frontend-dist/logo.svg
p8hub/frontend-dist/services.html
p8hub/frontend-dist/services.txt
p8hub/frontend-dist/_next/static/ATI5BIMBNnak1Tvlpvdhr/_buildManifest.js
p8hub/frontend-dist/_next/static/ATI5BIMBNnak1Tvlpvdhr/_ssgManifest.js
p8hub/frontend-dist/_next/static/chunks/0e5ce63c-75d812711d864f17.js
p8hub/frontend-dist/_next/static/chunks/13b76428-24f8ced979318ab8.js
p8hub/frontend-dist/_next/static/chunks/292-d67b9afcab9a78c8.js
p8hub/frontend-dist/_next/static/chunks/338-405b11d250039b23.js
p8hub/frontend-dist/_next/static/chunks/472-715790372ab7366b.js
p8hub/frontend-dist/_next/static/chunks/507-a9dbbc3e458a05c6.js
p8hub/frontend-dist/_next/static/chunks/64-2f1507f6f2a6c113.js
p8hub/frontend-dist/_next/static/chunks/894-97b02c137c79f4dc.js
p8hub/frontend-dist/_next/static/chunks/fd9d1056-c372703cb95ed2ee.js
p8hub/frontend-dist/_next/static/chunks/framework-8883d1e9be70c3da.js
p8hub/frontend-dist/_next/static/chunks/main-app-5a8432b1aa88f8b2.js
p8hub-0.0.4.dist-info/METADATA
p8hub-0.0.4.dist-info/WHEEL
p8hub-0.0.4.dist-info/entry_points.txt
p8hub-0.0.4.dist-info/top_level.txt
p8hub-0.0.4.dist-info/RECORD
