Metadata-Version: 2.1
Name: p8hub
Version: 0.0.4
Summary: Private AI Hub - Host your own Generative AI Services
Home-page: https://github.com/vietanhdev/p8hub
Author: Viet-Anh Nguyen
Author-email: vietanh.dev@gmail.com
License: Apache License 2.0
Keywords: Platform,Local,Generative AI,GPT,LLM,Stable Diffusion,Docker
Classifier: Natural Language :: English
Classifier: Operating System :: OS Independent
Classifier: Programming Language :: Python
Classifier: Programming Language :: Python :: 3.8
Classifier: Programming Language :: Python :: 3.9
Classifier: Programming Language :: Python :: 3.10
Classifier: Programming Language :: Python :: 3.11
Classifier: Programming Language :: Python :: 3 :: Only
Requires-Dist: urllib3 >=2.0.2
Requires-Dist: extract-msg >=0.41.1
Requires-Dist: tabulate >=0.9.0
Requires-Dist: python-multipart >=0.0.6
Requires-Dist: fastapi ==0.96.0
Requires-Dist: SQLAlchemy ==2.0.15
Requires-Dist: alembic ==1.11.1
Requires-Dist: requests ==2.31.0
Requires-Dist: uvicorn ==0.23.2
Requires-Dist: PyYAML ==6.0.1
Requires-Dist: psutil ==5.9.6
Requires-Dist: python-on-whales ==0.65.0
